{
    "title": "Управление активами",
    "questions": [
        {
            "question": "Все информационные активы организации идентифицированы и задокументированы?",
            "expected": true,
            "advice": "Создайте реестр информационных активов и поддерживайте его актуальность для обеспечения надлежащей защиты всех активов."
        },
        {
            "question": "Организация не классифицирует информацию по уровням важности и чувствительности?",
            "expected": false,
            "advice": "Внедрите классификацию информации по уровням важности и чувствительности для обеспечения адекватной защиты каждой категории информации."
        }
    ]
}